felips_counter/__init__.py
felips_counter/__main__.py
felips_counter/src/__init__.py
felips_counter/src/reader.py
felips_counter/src/writer.py
felips_counter/tests/__init__.py
felips_counter/tests/integration/__init__.py
felips_counter/tests/integration/test_ignore.py
felips_counter/tests/unit/__init__.py
felips_counter/tests/unit/test_reader.py
felips_counter/tests/unit/test_writer.py
felips_counter-1.0.10.dist-info/LICENSE
felips_counter-1.0.10.dist-info/METADATA
felips_counter-1.0.10.dist-info/WHEEL
felips_counter-1.0.10.dist-info/entry_points.txt
felips_counter-1.0.10.dist-info/top_level.txt
felips_counter-1.0.10.dist-info/RECORD
