Metadata-Version: 2.1
Name: felips-counter
Version: 1.0.10
Summary: Count your project lines easily!
Home-page: https://github.com/Blackoutseeker/Felips-Counter-Python
Author: Blackoutseeker (Felipe Pereira)
Author-email: felipsdev@gmail.com
License: MIT
Project-URL: Source, https://github.com/Blackoutseeker/Felips-Counter-Python
Project-URL: Funding, https://www.paypal.com/donate/?hosted_button_id=NEXQJS4U5HGC6
Project-URL: Tracker, https://github.com/Blackoutseeker/Felips-Counter-Python/issues
Keywords: blackoutseeker,felips,counter
Platform: win32
Platform: linux
Classifier: Development Status :: 5 - Production/Stable
Classifier: Intended Audience :: Developers
Classifier: Topic :: Utilities
Classifier: Topic :: Terminals
Classifier: License :: OSI Approved :: MIT License
Classifier: Programming Language :: Python :: 3
Classifier: Programming Language :: Python :: 3.7
Classifier: Programming Language :: Python :: 3.8
Classifier: Programming Language :: Python :: 3.9
Classifier: Programming Language :: Python :: 3.10
Classifier: Programming Language :: Python :: 3 :: Only
Classifier: Operating System :: Microsoft :: Windows
Requires-Python: >=3.7
License-File: LICENSE
Requires-Dist: colorama (~=0.4.6)
